squishyplanet/__init__.py
squishyplanet/limb_darkening_laws.py
squishyplanet/oblate_system.py
squishyplanet/engine/__init__.py
squishyplanet/engine/greens_basis_transform.py
squishyplanet/engine/kepler.py
squishyplanet/engine/parametric_ellipse.py
squishyplanet/engine/phase_curve_utils.py
squishyplanet/engine/planet_2d.py
squishyplanet/engine/planet_3d.py
squishyplanet/engine/polynomial_limb_darkened_transit.py
squishyplanet-0.3.1.dist-info/LICENSE
squishyplanet-0.3.1.dist-info/METADATA
squishyplanet-0.3.1.dist-info/WHEEL
squishyplanet-0.3.1.dist-info/top_level.txt
squishyplanet-0.3.1.dist-info/RECORD
