Metadata-Version: 2.1
Name: squishyplanet
Version: 0.3.1
Summary: A package for dealing with non-spherical exoplanets
Author-email: Ben Cassese <b.c.cassese@columbia.edu>
License: MIT
Project-URL: Homepage, https://github.com/ben-cassese/squishyplanet
Project-URL: Documentation, https://squishyplanet.readthedocs.io/en/latest/
Keywords: astronomy,exoplanets
Classifier: Programming Language :: Python
Classifier: Intended Audience :: Science/Research
Classifier: Topic :: Scientific/Engineering :: Astronomy
Requires-Python: >=3.9
License-File: LICENSE
Requires-Dist: requests
Requires-Dist: jax
Requires-Dist: jaxlib
Requires-Dist: quadax
Requires-Dist: tqdm
Requires-Dist: black
Requires-Dist: astropy >5
Requires-Dist: matplotlib
Requires-Dist: sympy
Requires-Dist: ipykernel
